Metadata-Version: 2.1
Name: demooMath
Version: 0.0.9
Summary: demo math package for testing
Home-page: UNKNOWN
Author: Sanyam Gupta
Author-email: sanyam233@gmail.com
License: UNKNOWN
Platform: UNKNOWN
Classifier: Development Status :: 1 - Planning
Classifier: Intended Audience :: Developers
Classifier: Programming Language :: Python :: 3
Classifier: Operating System :: Unix
Classifier: Operating System :: MacOS :: MacOS X
Classifier: Operating System :: Microsoft :: Windows
